{"pageContext":{"group":[{"node":{"id":"9435049d-00b9-5220-b081-ba85e0cd908e","slug":"blog-redone","status":"publish","template":"","format":"standard","title":"Blog redone","date":"2008-10-06T03:15:18.000Z"}},{"node":{"id":"b50ed7a1-8599-5c3f-ae5f-6bfb255edd80","slug":"god-and-science-dont-matter","status":"publish","template":"","format":"standard","title":"God and science don&#8217;t matter","date":"2008-10-02T14:35:18.000Z"}},{"node":{"id":"dfbb536a-ea9e-5252-9e0b-d395dec97716","slug":"boston-legal-is-a-huge-time-hog","status":"publish","template":"","format":"standard","title":"Boston Legal is a huge time hog","date":"2008-09-30T13:39:18.000Z"}}],"pathPrefix":"blog","first":false,"last":false,"index":312,"pageCount":434,"additionalContext":{}}}