{"data":{"wordpressPost":{"title":"Howto convince the iStore you&#8217;re from the US and circumvent regional copyright restrictions","content":"<div class=\"zemanta-img\" style=\"display: block; float: right; width: 207px; margin: 1em;\">\n<div>\n<dl class=\"wp-caption alignright\" style=\"width: 207px;\">\n<dt class=\"wp-caption-dt\"><a href=\"http://commons.wikipedia.org/wiki/Image:Green_copyright.svg\"><img title=\"Copyrighted\" src=\"http://upload.wikimedia.org/wikipedia/commons/thumb/5/57/Green_copyright.svg/197px-Green_copyright.svg.png\" alt=\"Copyrighted\" width=\"197\" height=\"197\" /></a></dt>\n<dd class=\"wp-caption-dd zemanta-img-attribution\" style=\"font-size: 0.8em;\">Image via <a href=\"http://commons.wikipedia.org/wiki/Image:Green_copyright.svg\">Wikipedia</a></dd>\n</dl>\n</div>\n</div>\n<p>Yesterday somebody shared a cool podcast with me.</p>\n<p>Well I should say they tried to, thing is, I didn&#8217;t have an iStore account. But whatever, I&#8217;ll just make one right? Well &#8230; no. That particular podcast is only available in the US due to copyright restrictions or something, or maybe it&#8217;s just that most of the store is US only, but whatever. Thing is, I had to make an account and I had to make an American one. Not a Slovene one.</p>\n<p>No biggie right, go to the iStore, make an account.</p>\n<p>Well no, you can&#8217;t choose where you&#8217;re from.</p>\n<p>So let&#8217;s change the language/locale to US and voila, american store. HEY even paypal is available now (yes we&#8217;ve got PayPal in Slovenia but Apple is an idiot and doesn&#8217;t aknowledge this fact).</p>\n<p>Yay, choose paypal, make account. Nope, says I&#8217;m not from the US. Fine, I&#8217;ll give you my credit card info &#8230; well fuck you mister Swizec, credit card says you&#8217;re not american. Fail.</p>\n<p>This is the process I had to go through to have a valid US Apple ID and iStore account.</p>\n<ol>\n<li>Find a free App.</li>\n<li>Download App.</li>\n<li>Create account</li>\n<li>Choose without CreditCard (they can&#8217;t demand payment info for free downloads, some legal stuff afaik)</li>\n<li>Enter some US address found on google maps (I used <a class=\"zem_slink\" title=\"M5 Industries\" rel=\"wikipedia\" href=\"http://en.wikipedia.org/wiki/M5_Industries\">M5 Industries</a> because <a class=\"zem_slink\" title=\"MythBusters\" rel=\"wikipedia\" href=\"http://en.wikipedia.org/wiki/MythBusters\">Mythbusters</a> is made there and I love Mythbusters). Btw this isn&#8217;t identity theft because you use your own name.</li>\n<li>Rejoice, you have a valid US iStore account</li>\n</ol>\n<p>Great! I can now download <strong>FREE</strong> stuff that is, for some strange and utterly absurd reason, only available in the US. Why have region restricted copyright when the content is bloody free is &#8230; can anyone explain this at all?</p>\n<div class=\"zemanta-pixie\" style=\"margin-top: 10px; height: 15px;\"><a class=\"zemanta-pixie-a\" title=\"Reblog this post [with Zemanta]\" href=\"http://reblog.zemanta.com/zemified/b7015c77-1a4f-4945-97ad-10b5f0edea2f/\"><img class=\"zemanta-pixie-img\" style=\"border: none; float: right;\" src=\"http://img.zemanta.com/reblog_e.png?x-id=b7015c77-1a4f-4945-97ad-10b5f0edea2f\" alt=\"Reblog this post [with Zemanta]\" /></a><span class=\"zem-script more-related pretty-attribution\"><script src=\"http://static.zemanta.com/readside/loader.js\" type=\"text/javascript\"></script></span></div>\n"},"site":{"siteMetadata":{"title":"Swizec Blog","subtitle":"Fetch Data From Local WP Install"}}},"pageContext":{"id":"ed2521f5-f07e-53ce-8436-993725612cb0"}}