{"pageContext":{"group":[{"node":{"id":"da063804-6d8c-523a-8f8d-53dca50b7697","slug":"arcane-javascript-knowledge-still-useful","status":"publish","template":"","format":"standard","title":"Arcane JavaScript knowledge still useful","date":"2017-11-17T15:22:07.000Z"}},{"node":{"id":"9665e725-865d-5357-8dba-f6bffb55d224","slug":"add-real-web-push-notifications-webapp","status":"publish","template":"","format":"standard","title":"How to add real web push notifications to your webapp","date":"2017-11-16T18:57:23.000Z"}},{"node":{"id":"5a4a4b63-ee00-54f9-b23d-d10404d2b6bf","slug":"vscode-better-editor-emacs","status":"publish","template":"","format":"standard","title":"After a week I must begrudgingly admit VSCode is a better editor than Emacs","date":"2017-11-10T20:22:07.000Z"}},{"node":{"id":"c91283f0-f46c-5a71-8713-16690a63cba0","slug":"livecoding-51-first-pr-big-oss-project","status":"publish","template":"","format":"standard","title":"Livecoding 51: I did it! My first PR to a big OSS project \\o/","date":"2017-11-09T19:50:13.000Z"}},{"node":{"id":"53c10e26-8650-505c-b825-81dd4ed77981","slug":"love-letter-prettier","status":"publish","template":"","format":"standard","title":"My love letter to Prettier","date":"2017-11-08T18:25:25.000Z"}},{"node":{"id":"b6fc4ab0-6701-527b-aaff-57250cfcb4c8","slug":"livecoding-recap-50-how-newbie-mistakes-kill-flow","status":"publish","template":"","format":"standard","title":"Livecoding Recap 50: How newbie mistakes kill the flow","date":"2017-11-06T15:15:45.000Z"}},{"node":{"id":"64de00ce-086c-525b-bd1e-9bcebf88fd2e","slug":"wont-be-switching-vscode","status":"publish","template":"","format":"standard","title":"Why I won&#8217;t be switching to VSCode any time soon","date":"2017-11-03T17:15:19.000Z"}},{"node":{"id":"daaa2ac9-8cf6-50f9-acda-4effc2759715","slug":"16661-october-sidehustle-report","status":"publish","template":"","format":"standard","title":"$16,863 October sidehustle report","date":"2017-11-02T15:15:28.000Z"}},{"node":{"id":"53e13c82-5bdd-5814-a05c-c74a8592bb6a","slug":"30","status":"publish","template":"","format":"standard","title":"30","date":"2017-10-31T19:49:05.000Z"}},{"node":{"id":"a93a450a-b48c-5bf4-b7aa-875c1b72abe6","slug":"simple-for-loop-increased-conversions","status":"publish","template":"","format":"standard","title":"That one time a simple for-loop increased conversions by 19%","date":"2017-10-20T16:13:20.000Z"}}],"pathPrefix":"","first":false,"last":false,"index":8,"pageCount":131,"additionalContext":{}}}