{"data":{"wordpressPost":{"title":"Zombi smrt","content":"<p>Internet je preplavljen z zombijevsko okuzbo in nasa dolznost je, da osvobodimo svet mrtve tiranije. Ce&nbsp;zelis&nbsp;pri&nbsp;tem&nbsp;cilju&nbsp;pomagati&nbsp;pojej&nbsp;modro&nbsp;tableto&nbsp;in&nbsp;pojdi&nbsp;<a href=\"http://www.crazymonkeygames.com/PlayBoxheadRooms.php\" target=\"_blank\">sem</a>.  </p>\n"},"site":{"siteMetadata":{"title":"Swizec Blog","subtitle":"Fetch Data From Local WP Install"}}},"pageContext":{"id":"4e0d3495-79fa-594f-a322-e49860dcc33c"}}