{"data":{"wordpressPost":{"title":"Pirati","content":"<p>V zadnjem èasu je internetno pazljivo oko se ¾e davno umaknilo s Piratov 2, ampak nekateri smo si jih ogledali &scaron;ele v soboto in zganili svoje riti &scaron;ele danes, da bi o njih kaj povedali, c&#8217;est la vie.</p>\n<p>Te¾ko se je odloèiti kam toèno bi uvrstil Pirate 2, na eni strani sem jaz, ljubitelj filmov, ki se dobro poslu&scaron;ajo, se pravi so prijetni za muziciranje v ozadju, na drugi strani pa sem jaz, ljubitelj posebnih efektov in velikih reèi. Prvi pirati so definitivno film, ki se odlièno poslu&scaron;a, veliko dobrega in zanimivega dialoga, ne preveè moteèih elementov in odlièna glasbena podlaga. Pirati 2 to definitivno niso, so èisto nasprotje tega, Pirati 2 so spektakel in za kaj veè bi jih bilo te¾ko jemati. Film je gledljiv nekako v stilu kot je gledljiv na primer Rambo, kaj veè bi pa bilo te¾ko prièakovati.</p>\n<p>Kar se tièe samih posebnih uèinkov pa kapo dol. vse skupaj je odlièno izpeljano, uporabljena je zanimiva tehnika, ki je tokrat res prinesla 3D animacije v takih detajlih kot verjetno &scaron;e lep èas ne bodo standard v filmih. Bral sem tudi nekaj èlankov o postopku dela in stvar je res sapo jemajoèa.</p>\n<p>Pri&scaron;li smo torej do dela novice, ki se dotika septemberskega stripa, &scaron;e vedno mi je ¾al za poletje brez novih delov.</p>\n<p>Strip je dobil lasten <span style=\"font-style: italic;\">storyboard</span>, ki je sluèajno tudi moj prvi. V izdelavo &scaron;e ni &scaron;el, ker moram najprej ustvariti tri dizajne ter se ponovno nauèiti kako se nari&scaron;e nekatere dotiène stvari, ki so se mi uspele nekako izmuzniti. Mislim, da lahko z skoraj&scaron;njo gotovostjo reèem, da bo strip narejen ob pravem èasu, kdaj toèno ta èas je pa naj ostane skrivnost.</p>\n"},"site":{"siteMetadata":{"title":"Swizec Blog","subtitle":"Fetch Data From Local WP Install"}}},"pageContext":{"id":"172caa1f-d130-561e-96da-6ce272718077"}}