{"pageContext":{"group":[{"node":{"id":"eeca0882-4802-50cb-91dd-11a8f8705693","slug":"tech-intern-job","status":"publish","template":"","format":"standard","title":"Tech intern job","date":"2018-06-10T02:23:10.000Z"}},{"node":{"id":"95c733f8-e874-5836-a27e-ccd61b7e6da6","slug":"ref-callbacks-measure-react-component-size","status":"publish","template":"","format":"standard","title":"Use ref callbacks to measure React component size","date":"2018-06-07T17:04:31.000Z"}},{"node":{"id":"e2ad5914-099b-5977-b4ea-48323c572bfa","slug":"tiny-react-d3-flamegraph-tutorial","status":"publish","template":"","format":"standard","title":"Tiny React &#038; D3 flamegraph tutorial","date":"2018-06-06T17:09:41.000Z"}},{"node":{"id":"71867501-9bd0-5872-bf09-5eac7042899f","slug":"build-animated-accordion-react-d3","status":"publish","template":"","format":"standard","title":"Build an animated pure SVG dynamic height accordion with React and D3","date":"2018-06-01T16:48:27.000Z"}},{"node":{"id":"23c1fb0f-71ea-50ef-9964-97a97ee86233","slug":"towards-webrtc-mesh-network-rtcdatachannel","status":"publish","template":"","format":"standard","title":"Towards a WebRTC mesh network with RTCDataChannel","date":"2018-05-30T17:04:43.000Z"}},{"node":{"id":"55536a52-0e4b-5777-aa3d-9ce0572f4d4a","slug":"learned-recording-educational-video-every-day","status":"publish","template":"","format":"standard","title":"Some tricks I learned recording &#038; publishing an educational video every day for 30 days","date":"2018-05-24T15:25:30.000Z"}},{"node":{"id":"20339ed7-18eb-5cd5-9dc8-3f9083e5b35f","slug":"tried-vr-plane-believer","status":"publish","template":"","format":"standard","title":"I tried VR on a plane and I&#8217;m a believer","date":"2018-05-22T16:41:50.000Z"}},{"node":{"id":"161f8832-4f3c-576d-9687-1715d8df190e","slug":"prepare-talk-8000-people-conference","status":"publish","template":"","format":"standard","title":"How I prepare for a talk at an 8,000 people conference","date":"2018-05-21T16:06:22.000Z"}},{"node":{"id":"6a2852ab-50ab-532a-8db7-792c8f7d91a3","slug":"learning-webrtc-peer-peer-communication-connecting-browsers-different-devices","status":"publish","template":"","format":"standard","title":"Learning WebRTC peer-to-peer communication, part 2 – connecting 2 browsers on different devices","date":"2018-05-16T15:01:07.000Z"}},{"node":{"id":"165a228e-7bbb-5369-b070-ce9d3796f05c","slug":"learned-microconf-growth-2018","status":"publish","template":"","format":"standard","title":"What I learned at MicroConf Growth 2018","date":"2018-05-10T17:12:39.000Z"}}],"pathPrefix":"posts","first":false,"last":false,"index":2,"pageCount":131,"additionalContext":{}}}